Workbook

Sheet Guía
B1: KOL Tracker — GenLayer Ambassadors & Rally
B3: Cómo usarlo
B4: 1. Alta de cada KOL en la hoja 'KOLs' (nombre, handle de X, programa, acuerdo y tarifa).
B5: 2. Cada vez que publiquen, añade una fila en 'Posts' con el link y las métricas (views, likes, RTs).
B6: 3. Registra cada pago (o pago comprometido) en 'Pagos' con su estado: Pagado o Pendiente.
B7: 4. 'Dashboard' y las columnas grises de 'KOLs' se calculan solas: no las edites.
B9: Código de colores
B10: • Fondo amarillo = celdas que rellenas tú.
B11: • Texto azul = datos introducidos a mano (los ejemplos incluidos están en azul).
B12: • Texto negro sin fondo = fórmulas automáticas, no tocar.
B14: Notas
B15: • Las filas marcadas '(ejemplo)' son de muestra: bórralas o sobreescríbelas con datos reales.
... B18: • CPM = coste pagado por cada 1.000 views atribuidas a ese KOL/programa.

Sheet Dashboard
A1: KOL Tracker — Dashboard
A2: Todo se calcula solo a partir de KOLs / Posts / Pagos.
A4: Totales
A5: KOLs activos | B5: =COUNTIF(KOLs!$H$2:$H$300,"Activo") -> 3
A6: Posts publicados | B6: =COUNTA(Posts!$A$2:$A$300) -> 4
A7: Views totales | B7: =SUM(Posts!$F$2:$F$300) -> 38900
A8: Total pagado ($) | B8: =SUMIF(Pagos!$F$2:$F$300,"Pagado",Pagos!$D$2:$D$300) -> 560
A9: Total pendiente ($) | B9: =SUMIF(Pagos!$F$2:$F$300,"Pendiente",Pagos!$D$2:$D$300) -> 800
A10: Coste por post ($) | B10: =IF(B6=0,"-",B8/B6) -> 140
A11: CPM ($/1k views) | B11: =IF(B7=0,"-",B8/B7*1000) -> 14.395887
A14: Por programa
A15: Programa | B15: KOLs activos | C15: Posts | D15: Views | E15: Pagado ($) | F15: Pendiente ($) | G15: Coste/post ($) | H15: CPM ($/1k)
A16: GenLayer Ambassador | B16: =COUNTIFS(KOLs!$D$2:$D$300,$A16,KOLs!$H$2:$H$300,"Activo") -> 2 | C16: =COUNTIF(Posts!$C$2:$C$300,$A16) -> 3 | D16: =SUMIF(Posts!$C$2:$C$300,$A16,Posts!$F$2:$F$300) -> 18800 | E16: =SUMIFS(Pagos!$D$2:$D$300,Pagos!$C$2:$C$300,$A16,Pagos!$F$2:$F$300,"Pagado") -> 560 | F16: =SUMIFS(Pagos!$D$2:$D$300,Pagos!$C$2:$C$300,$A16,Pagos!$F$2:$F$300,"Pendiente") -> 0 | G16: =IF(C16=0,"-",E16/C16) -> 186.66667 | H16: =IF(D16=0,"-",E16/D16*1000) -> 29.787234
A17: Rally | B17: =COUNTIFS(KOLs!$D$2:$D$300,$A17,KOLs!$H$2:$H$300,"Activo") -> 1 | C17: =COUNTIF(Posts!$C$2:$C$300,$A17) -> 1 | D17: =SUMIF(Posts!$C$2:$C$300,$A17,Posts!$F$2:$F$300) -> 20100 | E17: =SUMIFS(Pagos!$D$2:$D$300,Pagos!$C$2:$C$300,$A17,Pagos!$F$2:$F$300,"Pagado") -> 0 | F17: =SUMIFS(Pagos!$D$2:$D$300,Pagos!$C$2:$C$300,$A17,Pagos!$F$2:$F$300,"Pendiente") -> 800 | G17: =IF(C17=0,"-",E17/C17) -> 0 | H17: =IF(D17=0,"-",E17/D17*1000) -> 0
A20: El detalle por KOL (posts, pagado, pendiente, CPM) está en las columnas grises de la hoja 'KOLs'.

Sheet KOLs
A1: Nombre | B1: Handle X | C1: Link X | D1: Programa | E1: Tipo de acuerdo | F1: Tarifa ($) | G1: Fecha inicio | H1: Estado | I1: Wallet / método de pago | J1: Notas | K1: Nº posts | L1: Views totales | M1: Total pagado ($) | N1: Pendiente ($) | O1: CPM ($/1k views)
A2: Ana Ejemplo | B2: @ana_web3 | C2: https://x.com/ana_web3 | D2: GenLayer Ambassador | E2: Fijo mensual | F2: 500 | G2: 2026-06-01 | H2: Activo | I2: USDC 0x1234…abcd | J2: (ejemplo) borrar | K2: =IF(A2="","",COUNTIF(Posts!$B$2:$B$300,A2)) -> 2 | L2: =IF(A2="","",SUMIF(Posts!$B$2:$B$300,A2,Posts!$F$2:$F$300)) -> 14500 | M2: =IF(A2="","",SUMIFS(Pagos!$D$2:$D$300,Pagos!$B$2:$B$300,A2,Pagos!$F$2:$F$300,"Pagado")) -> 500 | N2: =IF(A2="","",SUMIFS(Pagos!$D$2:$D$300,Pagos!$B$2:$B$300,A2,Pagos!$F$2:$F$300,"Pendiente")) -> 0 | O2: =IF(A2="","",IF(L2=0,"-",M2/L2*1000)) -> 34.482759
A3: Bruno Ejemplo | B3: @brunocripto | C3: https://x.com/brunocripto | D3: GenLayer Ambassador | E3: Por post | F3: 60 | G3: 2026-06-15 | H3: Activo | I3: PayPal bruno@mail.com | J3: (ejemplo) borrar | K3: =IF(A3="","",COUNTIF(Posts!$B$2:$B$300,A3)) -> 1 | L3: =IF(A3="","",SUMIF(Posts!$B$2:$B$300,A3,Posts!$F$2:$F$300)) -> 4300 | M3: =IF(A3="","",SUMIFS(Pagos!$D$2:$D$300,Pagos!$B$2:$B$300,A3,Pagos!$F$2:$F$300,"Pagado")) -> 60 | N3: =IF(A3="","",SUMIFS(Pagos!$D$2:$D$300,Pagos!$B$2:$B$300,A3,Pagos!$F$2:$F$300,"Pendiente")) -> 0 | O3: =IF(A3="","",IF(L3=0,"-",M3/L3*1000)) -> 13.953488
A4: Carla Ejemplo | B4: @carla_defi | C4: https://x.com/carla_defi | D4: Rally | E4: Fijo mensual | F4: 800 | G4: 2026-07-01 | H4: Activo | I4: USDT 0x9876…ff00 | J4: (ejemplo) borrar | K4: =IF(A4="","",COUNTIF(Posts!$B$2:$B$300,A4)) -> 1 | L4: =IF(A4="","",SUMIF(Posts!$B$2:$B$300,A4,Posts!$F$2:$F$300)) -> 20100 | M4: =IF(A4="","",SUMIFS(Pagos!$D$2:$D$300,Pagos!$B$2:$B$300,A4,Pagos!$F$2:$F$300,"Pagado")) -> 0 | N4: =IF(A4="","",SUMIFS(Pagos!$D$2:$D$300,Pagos!$B$2:$B$300,A4,Pagos!$F$2:$F$300,"Pendiente")) -> 800 | O4: =IF(A4="","",IF(L4=0,"-",M4/L4*1000)) -> 0
K5: =IF(A5="","",COUNTIF(Posts!$B$2:$B$300,A5)) | L5: =IF(A5="","",SUMIF(Posts!$B$2:$B$300,A5,Posts!$F$2:$F$300)) | M5: =IF(A5="","",SUMIFS(Pagos!$D$2:$D$300,Pagos!$B$2:$B$300,A5,Pagos!$F$2:$F$300,"Pagado")) | N5: =IF(A5="","",SUMIFS(Pagos!$D$2:$D$300,Pagos!$B$2:$B$300,A5,Pagos!$F$2:$F$300,"Pendiente")) | O5: =IF(A5="","",IF(L5=0,"-",M5/L5*1000))
K6: =IF(A6="","",COUNTIF(Posts!$B$2:$B$300,A6)) | L6: =IF(A6="","",SUMIF(Posts!$B$2:$B$300,A6,Posts!$F$2:$F$300)) | M6: =IF(A6="","",SUMIFS(Pagos!$D$2:$D$300,Pagos!$B$2:$B$300,A6,Pagos!$F$2:$F$300,"Pagado")) | N6: =IF(A6="","",SUMIFS(Pagos!$D$2:$D$300,Pagos!$B$2:$B$300,A6,Pagos!$F$2:$F$300,"Pendiente")) | O6: =IF(A6="","",IF(L6=0,"-",M6/L6*1000))
K7: =IF(A7="","",COUNTIF(Posts!$B$2:$B$300,A7)) | L7: =IF(A7="","",SUMIF(Posts!$B$2:$B$300,A7,Posts!$F$2:$F$300)) | M7: =IF(A7="","",SUMIFS(Pagos!$D$2:$D$300,Pagos!$B$2:$B$300,A7,Pagos!$F$2:$F$300,"Pagado")) | N7: =IF(A7="","",SUMIFS(Pagos!$D$2:$D$300,Pagos!$B$2:$B$300,A7,Pagos!$F$2:$F$300,"Pendiente")) | O7: =IF(A7="","",IF(L7=0,"-",M7/L7*1000))
K8: =IF(A8="","",COUNTIF(Posts!$B$2:$B$300,A8)) | L8: =IF(A8="","",SUMIF(Posts!$B$2:$B$300,A8,Posts!$F$2:$F$300)) | M8: =IF(A8="","",SUMIFS(Pagos!$D$2:$D$300,Pagos!$B$2:$B$300,A8,Pagos!$F$2:$F$300,"Pagado")) | N8: =IF(A8="","",SUMIFS(Pagos!$D$2:$D$300,Pagos!$B$2:$B$300,A8,Pagos!$F$2:$F$300,"Pendiente")) | O8: =IF(A8="","",IF(L8=0,"-",M8/L8*1000))
K9: =IF(A9="","",COUNTIF(Posts!$B$2:$B$300,A9)) | L9: =IF(A9="","",SUMIF(Posts!$B$2:$B$300,A9,Posts!$F$2:$F$300)) | M9: =IF(A9="","",SUMIFS(Pagos!$D$2:$D$300,Pagos!$B$2:$B$300,A9,Pagos!$F$2:$F$300,"Pagado")) | N9: =IF(A9="","",SUMIFS(Pagos!$D$2:$D$300,Pagos!$B$2:$B$300,A9,Pagos!$F$2:$F$300,"Pendiente")) | O9: =IF(A9="","",IF(L9=0,"-",M9/L9*1000))
K10: =IF(A10="","",COUNTIF(Posts!$B$2:$B$300,A10)) | L10: =IF(A10="","",SUMIF(Posts!$B$2:$B$300,A10,Posts!$F$2:$F$300)) | M10: =IF(A10="","",SUMIFS(Pagos!$D$2:$D$300,Pagos!$B$2:$B$300,A10,Pagos!$F$2:$F$300,"Pagado")) | N10: =IF(A10="","",SUMIFS(Pagos!$D$2:$D$300,Pagos!$B$2:$B$300,A10,Pagos!$F$2:$F$300,"Pendiente")) | O10: =IF(A10="","",IF(L10=0,"-",M10/L10*1000))
K11: =IF(A11="","",COUNTIF(Posts!$B$2:$B$300,A11)) | L11: =IF(A11="","",SUMIF(Posts!$B$2:$B$300,A11,Posts!$F$2:$F$300)) | M11: =IF(A11="","",SUMIFS(Pagos!$D$2:$D$300,Pagos!$B$2:$B$300,A11,Pagos!$F$2:$F$300,"Pagado")) | N11: =IF(A11="","",SUMIFS(Pagos!$D$2:$D$300,Pagos!$B$2:$B$300,A11,Pagos!$F$2:$F$300,"Pendiente")) | O11: =IF(A11="","",IF(L11=0,"-",M11/L11*1000))
K12: =IF(A12="","",COUNTIF(Posts!$B$2:$B$300,A12)) | L12: =IF(A12="","",SUMIF(Posts!$B$2:$B$300,A12,Posts!$F$2:$F$300)) | M12: =IF(A12="","",SUMIFS(Pagos!$D$2:$D$300,Pagos!$B$2:$B$300,A12,Pagos!$F$2:$F$300,"Pagado")) | N12: =IF(A12="","",SUMIFS(Pagos!$D$2:$D$300,Pagos!$B$2:$B$300,A12,Pagos!$F$2:$F$300,"Pendiente")) | O12: =IF(A12="","",IF(L12=0,"-",M12/L12*1000))
K13: =IF(A13="","",COUNTIF(Posts!$B$2:$B$300,A13)) | L13: =IF(A13="","",SUMIF(Posts!$B$2:$B$300,A13,Posts!$F$2:$F$300)) | M13: =IF(A13="","",SUMIFS(Pagos!$D$2:$D$300,Pagos!$B$2:$B$300,A13,Pagos!$F$2:$F$300,"Pagado")) | N13: =IF(A13="","",SUMIFS(Pagos!$D$2:$D$300,Pagos!$B$2:$B$300,A13,Pagos!$F$2:$F$300,"Pendiente")) | O13: =IF(A13="","",IF(L13=0,"-",M13/L13*1000))
K14: =IF(A14="","",COUNTIF(Posts!$B$2:$B$300,A14)) | L14: =IF(A14="","",SUMIF(Posts!$B$2:$B$300,A14,Posts!$F$2:$F$300)) | M14: =IF(A14="","",SUMIFS(Pagos!$D$2:$D$300,Pagos!$B$2:$B$300,A14,Pagos!$F$2:$F$300,"Pagado")) | N14: =IF(A14="","",SUMIFS(Pagos!$D$2:$D$300,Pagos!$B$2:$B$300,A14,Pagos!$F$2:$F$300,"Pendiente")) | O14: =IF(A14="","",IF(L14=0,"-",M14/L14*1000))
K15: =IF(A15="","",COUNTIF(Posts!$B$2:$B$300,A15)) | L15: =IF(A15="","",SUMIF(Posts!$B$2:$B$300,A15,Posts!$F$2:$F$300)) | M15: =IF(A15="","",SUMIFS(Pagos!$D$2:$D$300,Pagos!$B$2:$B$300,A15,Pagos!$F$2:$F$300,"Pagado")) | N15: =IF(A15="","",SUMIFS(Pagos!$D$2:$D$300,Pagos!$B$2:$B$300,A15,Pagos!$F$2:$F$300,"Pendiente")) | O15: =IF(A15="","",IF(L15=0,"-",M15/L15*1000))
K16: =IF(A16="","",COUNTIF(Posts!$B$2:$B$300,A16)) | L16: =IF(A16="","",SUMIF(Posts!$B$2:$B$300,A16,Posts!$F$2:$F$300)) | M16: =IF(A16="","",SUMIFS(Pagos!$D$2:$D$300,Pagos!$B$2:$B$300,A16,Pagos!$F$2:$F$300,"Pagado")) | N16: =IF(A16="","",SUMIFS(Pagos!$D$2:$D$300,Pagos!$B$2:$B$300,A16,Pagos!$F$2:$F$300,"Pendiente")) | O16: =IF(A16="","",IF(L16=0,"-",M16/L16*1000))
... K300: =IF(A300="","",COUNTIF(Posts!$B$2:$B$300,A300)) | L300: =IF(A300="","",SUMIF(Posts!$B$2:$B$300,A300,Posts!$F$2:$F$300)) | M300: =IF(A300="","",SUMIFS(Pagos!$D$2:$D$300,Pagos!$B$2:$B$300,A300,Pagos!$F$2:$F$300,"Pagado")) | N300: =IF(A300="","",SUMIFS(Pagos!$D$2:$D$300,Pagos!$B$2:$B$300,A300,Pagos!$F$2:$F$300,"Pendiente")) | O300: =IF(A300="","",IF(L300=0,"-",M300/L300*1000))

Sheet Posts
A1: Fecha | B1: KOL | C1: Programa (auto) | D1: Link al post | E1: Tipo | F1: Views | G1: Likes | H1: RTs | I1: Comentarios | J1: Coste atribuido ($) | K1: Notas
A2: 2026-07-05 | B2: Ana Ejemplo | C2: =IF(B2="","",IFERROR(INDEX(KOLs!$D$2:$D$300,MATCH(B2,KOLs!$A$2:$A$300,0)),"¿KOL no dado de alta?")) -> GenLayer Ambassador | D2: https://x.com/ana_web3/status/111 | E2: Hilo | F2: 12400 | G2: 310 | H2: 85 | I2: 40 | J2: 0 | K2: (ejemplo) incluido en fijo mensual
A3: 2026-07-10 | B3: Bruno Ejemplo | C3: =IF(B3="","",IFERROR(INDEX(KOLs!$D$2:$D$300,MATCH(B3,KOLs!$A$2:$A$300,0)),"¿KOL no dado de alta?")) -> GenLayer Ambassador | D3: https://x.com/brunocripto/status/222 | E3: Post | F3: 4300 | G3: 120 | H3: 22 | I3: 9 | J3: 60 | K3: (ejemplo) pagado por post
A4: 2026-07-12 | B4: Carla Ejemplo | C4: =IF(B4="","",IFERROR(INDEX(KOLs!$D$2:$D$300,MATCH(B4,KOLs!$A$2:$A$300,0)),"¿KOL no dado de alta?")) -> Rally | D4: https://x.com/carla_defi/status/333 | E4: Post | F4: 20100 | G4: 540 | H4: 130 | I4: 55 | J4: 0 | K4: (ejemplo) incluido en fijo mensual
A5: 2026-07-20 | B5: Ana Ejemplo | C5: =IF(B5="","",IFERROR(INDEX(KOLs!$D$2:$D$300,MATCH(B5,KOLs!$A$2:$A$300,0)),"¿KOL no dado de alta?")) -> GenLayer Ambassador | D5: https://x.com/ana_web3/status/444 | E5: Space | F5: 2100 | G5: 60 | H5: 10 | I5: 5 | J5: 0 | K5: (ejemplo)
C6: =IF(B6="","",IFERROR(INDEX(KOLs!$D$2:$D$300,MATCH(B6,KOLs!$A$2:$A$300,0)),"¿KOL no dado de alta?"))
C7: =IF(B7="","",IFERROR(INDEX(KOLs!$D$2:$D$300,MATCH(B7,KOLs!$A$2:$A$300,0)),"¿KOL no dado de alta?"))
C8: =IF(B8="","",IFERROR(INDEX(KOLs!$D$2:$D$300,MATCH(B8,KOLs!$A$2:$A$300,0)),"¿KOL no dado de alta?"))
C9: =IF(B9="","",IFERROR(INDEX(KOLs!$D$2:$D$300,MATCH(B9,KOLs!$A$2:$A$300,0)),"¿KOL no dado de alta?"))
C10: =IF(B10="","",IFERROR(INDEX(KOLs!$D$2:$D$300,MATCH(B10,KOLs!$A$2:$A$300,0)),"¿KOL no dado de alta?"))
C11: =IF(B11="","",IFERROR(INDEX(KOLs!$D$2:$D$300,MATCH(B11,KOLs!$A$2:$A$300,0)),"¿KOL no dado de alta?"))
C12: =IF(B12="","",IFERROR(INDEX(KOLs!$D$2:$D$300,MATCH(B12,KOLs!$A$2:$A$300,0)),"¿KOL no dado de alta?"))
C13: =IF(B13="","",IFERROR(INDEX(KOLs!$D$2:$D$300,MATCH(B13,KOLs!$A$2:$A$300,0)),"¿KOL no dado de alta?"))
C14: =IF(B14="","",IFERROR(INDEX(KOLs!$D$2:$D$300,MATCH(B14,KOLs!$A$2:$A$300,0)),"¿KOL no dado de alta?"))
C15: =IF(B15="","",IFERROR(INDEX(KOLs!$D$2:$D$300,MATCH(B15,KOLs!$A$2:$A$300,0)),"¿KOL no dado de alta?"))
C16: =IF(B16="","",IFERROR(INDEX(KOLs!$D$2:$D$300,MATCH(B16,KOLs!$A$2:$A$300,0)),"¿KOL no dado de alta?"))
C17: =IF(B17="","",IFERROR(INDEX(KOLs!$D$2:$D$300,MATCH(B17,KOLs!$A$2:$A$300,0)),"¿KOL no dado de alta?"))
... C300: =IF(B300="","",IFERROR(INDEX(KOLs!$D$2:$D$300,MATCH(B300,KOLs!$A$2:$A$300,0)),"¿KOL no dado de alta?"))

Sheet Pagos
A1: Fecha | B1: KOL | C1: Programa (auto) | D1: Importe ($) | E1: Concepto | F1: Estado | G1: Método / tx | H1: Notas
A2: 2026-07-01 | B2: Ana Ejemplo | C2: =IF(B2="","",IFERROR(INDEX(KOLs!$D$2:$D$300,MATCH(B2,KOLs!$A$2:$A$300,0)),"¿KOL no dado de alta?")) -> GenLayer Ambassador | D2: 500 | E2: Fijo mensual julio | F2: Pagado | G2: USDC tx 0xaaa… | H2: (ejemplo)
A3: 2026-07-15 | B3: Bruno Ejemplo | C3: =IF(B3="","",IFERROR(INDEX(KOLs!$D$2:$D$300,MATCH(B3,KOLs!$A$2:$A$300,0)),"¿KOL no dado de alta?")) -> GenLayer Ambassador | D3: 60 | E3: Post 2026-07-10 | F3: Pagado | G3: PayPal | H3: (ejemplo)
A4: 2026-08-01 | B4: Carla Ejemplo | C4: =IF(B4="","",IFERROR(INDEX(KOLs!$D$2:$D$300,MATCH(B4,KOLs!$A$2:$A$300,0)),"¿KOL no dado de alta?")) -> Rally | D4: 800 | E4: Fijo mensual julio | F4: Pendiente | H4: (ejemplo)
C5: =IF(B5="","",IFERROR(INDEX(KOLs!$D$2:$D$300,MATCH(B5,KOLs!$A$2:$A$300,0)),"¿KOL no dado de alta?"))
C6: =IF(B6="","",IFERROR(INDEX(KOLs!$D$2:$D$300,MATCH(B6,KOLs!$A$2:$A$300,0)),"¿KOL no dado de alta?"))
C7: =IF(B7="","",IFERROR(INDEX(KOLs!$D$2:$D$300,MATCH(B7,KOLs!$A$2:$A$300,0)),"¿KOL no dado de alta?"))
C8: =IF(B8="","",IFERROR(INDEX(KOLs!$D$2:$D$300,MATCH(B8,KOLs!$A$2:$A$300,0)),"¿KOL no dado de alta?"))
C9: =IF(B9="","",IFERROR(INDEX(KOLs!$D$2:$D$300,MATCH(B9,KOLs!$A$2:$A$300,0)),"¿KOL no dado de alta?"))
C10: =IF(B10="","",IFERROR(INDEX(KOLs!$D$2:$D$300,MATCH(B10,KOLs!$A$2:$A$300,0)),"¿KOL no dado de alta?"))
C11: =IF(B11="","",IFERROR(INDEX(KOLs!$D$2:$D$300,MATCH(B11,KOLs!$A$2:$A$300,0)),"¿KOL no dado de alta?"))
C12: =IF(B12="","",IFERROR(INDEX(KOLs!$D$2:$D$300,MATCH(B12,KOLs!$A$2:$A$300,0)),"¿KOL no dado de alta?"))
C13: =IF(B13="","",IFERROR(INDEX(KOLs!$D$2:$D$300,MATCH(B13,KOLs!$A$2:$A$300,0)),"¿KOL no dado de alta?"))
C14: =IF(B14="","",IFERROR(INDEX(KOLs!$D$2:$D$300,MATCH(B14,KOLs!$A$2:$A$300,0)),"¿KOL no dado de alta?"))
C15: =IF(B15="","",IFERROR(INDEX(KOLs!$D$2:$D$300,MATCH(B15,KOLs!$A$2:$A$300,0)),"¿KOL no dado de alta?"))
C16: =IF(B16="","",IFERROR(INDEX(KOLs!$D$2:$D$300,MATCH(B16,KOLs!$A$2:$A$300,0)),"¿KOL no dado de alta?"))
... C300: =IF(B300="","",IFERROR(INDEX(KOLs!$D$2:$D$300,MATCH(B300,KOLs!$A$2:$A$300,0)),"¿KOL no dado de alta?"))
